chopsticks/__init__.py
chopsticks/bubble.py
chopsticks/facts.py
chopsticks/group.py
chopsticks/helpers.py
chopsticks/ioloop.py
chopsticks/queue.py
chopsticks/serialise_main.py
chopsticks/setops.py
chopsticks/streams.py
chopsticks/tunnel.py
chopsticks-1.0.dist-info/DESCRIPTION.rst
chopsticks-1.0.dist-info/METADATA
chopsticks-1.0.dist-info/RECORD
chopsticks-1.0.dist-info/WHEEL
chopsticks-1.0.dist-info/metadata.json
chopsticks-1.0.dist-info/top_level.txt
