Metadata-Version: 2.0
Name: chopsticks
Version: 1.0
Summary: Chopsticks is an orchestration library: it lets you manage and configure remote hosts over SSH.
Home-page: https://github.com/lordmauve/chopsticks
Author: Daniel Pope
Author-email: mauve@mauveweb.co.uk
License: UNKNOWN
Platform: UNKNOWN
Classifier: Development Status :: 4 - Beta
Classifier: Intended Audience :: Developers
Classifier: Intended Audience :: System Administrators
Classifier: Programming Language :: Python :: 2
Classifier: Programming Language :: Python :: 3
Classifier: Operating System :: POSIX
Classifier: License :: OSI Approved :: Apache Software License
Classifier: Topic :: System :: Systems Administration
